{
    "width": 256,
    "height": 512,
    "Down": {
        "Stand": [[99, 163], [155, 86]],
        "Walk": [
            [[11, 163], [69, 87]],
            [[185, 163], [243, 87]]
        ]
    },
    "Left": {
        "Stand": [[104, 249], [152, 172]],
        "Walk": [
            [[18, 249], [66, 173]],
            [[190, 249], [237, 173]]
        ]
    },
    "Right": {
        "Stand": [[102, 335], [150, 257]],
        "Walk": [
            [[17, 335], [64, 259]],
            [[188, 335], [236, 259]]
        ]
    },
    "Up": {
        "Stand": [[99, 421], [155, 344]],
        "Walk": [
            [[11, 421], [69, 345]],
            [[185, 421], [243, 345]]
        ]
    }
}
