{
    "Camera": [
        {
            "Center": [100, 56.25],
            "Width": 200,
            "Viewport": [0, 0, 1280, 720],
            "BgColor": [0.9, 0.9, 0.9, 1.0]
        }
    ],
    
    "Hero": {
        "Position": [10, 84],
        "Scale": [3, 7.5],
        "MoveSpeed": 45,
        "JumpSpeed": 75
    },
    
    "Catherine": {
        "Position": [170, 84],
        "Scale": [3, 7.5],
        "Speed": 0.5,
        "TriggerDistance": 40
    },
    
    "Humans" :[
        {
        "Position": [45, 59],
        "Scale": [3, 7.5],
        "Speed": 0.3,
        "TriggerDistance": 40
        },
        {
        "Position": [85, 59],
        "Scale": [3, 7.5],
        "Speed": 0.3,
        "TriggerDistance": 40
        },
        {
        "Position": [70, 10],
        "Scale": [3, 7.5],
        "Speed": 0.3,
        "TriggerDistance": 40
        },
        {
        "Position": [25, 34],
        "Scale": [3, 7.5],
        "Speed": 0.3,
        "TriggerDistance": 40
        },
        {
        "Position": [120, 34],
        "Scale": [3, 7.5],
        "Speed": 0.3,
        "TriggerDistance": 40
        },
        {
        "Position": [160, 84],
        "Scale": [3, 7.5],
        "Speed": 0.3,
        "TriggerDistance": 40
        }
    ],
    
    "Flower": {
        "Position": [100, 8],
        "Scale": [8, 8]
    },
    
    "Platforms": [
        {
            "Position": [100, -35],
            "Scale": [200, 2]
        },
        {
            "Position": [100, 3],
            "Scale": [200, 2]
        },
        {
            "Position": [140, 27],
            "Scale": [120, 2]
        },
        {
            "Position": [20, 27],
            "Scale": [40, 2]
        },
        {
            "Position": [100, 52],
            "Scale": [160, 2]
        },
        {
            "Position": [20, 77],
            "Scale": [40, 2]
        },
        {
            "Position": [150, 77],
            "Scale": [100, 2]
        }
    ],
    
    "Walls": [
        {
            "Position": [0, 30],
            "Scale": [1, 170]
        },
        {
            "Position": [200, 30],
            "Scale": [1, 170]
        }
    ],
    
        "Texts" :[
        {
            "Content": "There were lots of other humans",
            "Position": [55, 107],
            "Color": [0.9, 0.9, 0.9, 1.0],
            "Height": 5
        },
        {
            "Content": "Fortunately I could jump higher than them",
            "Position": [42, 100],
            "Color": [0.9, 0.9, 0.9, 1.0],
            "Height": 5
        }
    ],
    
    "GameStatus": {
        "DefaultStatus": 0
    }
}
